{"cameraMode":{"drawMode":0,"name":"Shaded","section":"Shading Mode"},"sceneLighting":true,"audioPlay":false,"sceneViewState":{"showFog":true,"showMaterialUpdate":false,"showSkybox":true,"showFlares":true,"showImageEffects":true,"showParticleSystems":true,"showVisualEffectGraphs":true,"m_FxEnabled":true},"in2DMode":false,"pivot":{"x":2.301114082336426,"y":1.8034428358078004,"z":0.6711886525154114},"rotation":{"x":0.2621680200099945,"y":-0.6691136360168457,"z":0.2745746076107025,"w":0.6388918161392212},"size":7.18049430847168,"orthographic":false}